Metadata-Version: 2.1
Name: pertsev-krogh-interpolator
Version: 0.1.0
Summary: My realisation of Krogh interpolator
Home-page: https://github.com/pertsevpv
Author: Pertsev Pavel
Author-email: pertsevpv@gmail.com
License: BSD 2-clause
Platform: UNKNOWN
Classifier: Development Status :: 1 - Planning
Classifier: Intended Audience :: Science/Research
Classifier: License :: OSI Approved :: BSD License
Classifier: Operating System :: POSIX :: Linux
Classifier: Programming Language :: Python :: 2
Classifier: Programming Language :: Python :: 2.7
Classifier: Programming Language :: Python :: 3
Classifier: Programming Language :: Python :: 3.4
Classifier: Programming Language :: Python :: 3.5
